oss_redteam/__init__.py
oss_redteam/harness.py
oss_redteam/pipeline.py
oss_redteam/tool_schemas.py
oss_redteam-0.1.1.dist-info/licenses/LICENSE
oss_redteam-0.1.1.dist-info/METADATA
oss_redteam-0.1.1.dist-info/WHEEL
oss_redteam-0.1.1.dist-info/entry_points.txt
oss_redteam-0.1.1.dist-info/top_level.txt
oss_redteam-0.1.1.dist-info/RECORD
