Metadata-Version: 2.4
Name: oss-redteam
Version: 0.1.1
Summary: GPT-OSS red-teaming pipeline and harness (OpenAI-compatible)
Author: OSS Redteam Authors
License: MIT License
Project-URL: Homepage, https://github.com/kpower7/oss-testing
Project-URL: Repository, https://github.com/kpower7/oss-testing
Project-URL: Issues, https://github.com/kpower7/oss-testing/issues
Keywords: redteam,oss,openai,tool-calling,safety,evaluation
Classifier: License :: OSI Approved :: MIT License
Classifier: Programming Language :: Python :: 3
Classifier: Programming Language :: Python :: 3 :: Only
Classifier: Programming Language :: Python :: 3.9
Classifier: Programming Language :: Python :: 3.10
Classifier: Programming Language :: Python :: 3.11
Classifier: Programming Language :: Python :: 3.12
Classifier: Operating System :: OS Independent
Classifier: Topic :: Scientific/Engineering :: Artificial Intelligence
Requires-Python: >=3.9
License-File: LICENSE
Requires-Dist: openai>=1.40.0
Requires-Dist: python-dotenv>=1.0.1
Dynamic: license-file
